solugenerics/__init__.py
solugenerics/env_manager/__init__.py
solugenerics/env_manager/main.py
solugenerics/generic_flask_response/__init__.py
solugenerics/generic_flask_response/main.py
solugenerics/solooger/__init__.py
solugenerics/solooger/main.py
solugenerics-0.5.6.dist-info/METADATA
solugenerics-0.5.6.dist-info/WHEEL
solugenerics-0.5.6.dist-info/top_level.txt
solugenerics-0.5.6.dist-info/RECORD
