Metadata-Version: 2.1
Name: solugenerics
Version: 0.5.6
Summary: Reusable tools for Solugen workers
Home-page: https://pypi.org/project/solugenerics/
Author: Elad Laor
Author-email: elad.l@solugen.ai
License: MIT
Classifier: Programming Language :: Python :: 3
Classifier: License :: OSI Approved :: MIT License
Classifier: Operating System :: OS Independent
Requires-Python: >=3.6
Requires-Dist: Flask>=2.0.0
Requires-Dist: python-dotenv==1.0.1
Requires-Dist: loguru==0.7.2
